automlst/cli/__init__.py
automlst/cli/info.py
automlst/cli/meta.py
automlst/cli/program.py
automlst/cli/st.py
automlst.cli-0.2.0.dist-info/METADATA
automlst.cli-0.2.0.dist-info/WHEEL
automlst.cli-0.2.0.dist-info/entry_points.txt
automlst.cli-0.2.0.dist-info/top_level.txt
automlst.cli-0.2.0.dist-info/RECORD
