Metadata-Version: 2.2
Name: automlst.cli
Version: 0.2.0
Summary: A CLI tool to rapidly fetch fetch MLST profiles given sequences for various diseases.
Requires-Python: >=3.11
Requires-Dist: automlst-engine
